MANIFEST.in
README.txt
setup.cfg
setup.py
docs/HISTORY.txt
docs/TODO.txt
docs/api/html/api-objects.txt
docs/api/html/class-tree.html
docs/api/html/crarr.png
docs/api/html/epydoc.css
docs/api/html/epydoc.js
docs/api/html/frames.html
docs/api/html/help.html
docs/api/html/identifier-index.html
docs/api/html/index.html
docs/api/html/konval-module.html
docs/api/html/konval-pysrc.html
docs/api/html/konval.basevalidator-module.html
docs/api/html/konval.basevalidator-pysrc.html
docs/api/html/konval.basevalidator.BaseValidator-class.html
docs/api/html/konval.basevalidator.WrappingValidator-class.html
docs/api/html/konval.containerval-module.html
docs/api/html/konval.containerval-pysrc.html
docs/api/html/konval.containerval.CheckLength-class.html
docs/api/html/konval.containerval.IsEmpty-class.html
docs/api/html/konval.containerval.IsMember-class.html
docs/api/html/konval.containerval.IsNotEmpty-class.html
docs/api/html/konval.containerval.ToIndex-class.html
docs/api/html/konval.containerval.ToLength-class.html
docs/api/html/konval.defs-module.html
docs/api/html/konval.defs-pysrc.html
docs/api/html/konval.fxn-module.html
docs/api/html/konval.fxn-pysrc.html
docs/api/html/konval.impl-module.html
docs/api/html/konval.impl-pysrc.html
docs/api/html/konval.internetval-module.html
docs/api/html/konval.internetval-pysrc.html
docs/api/html/konval.sizeval-module.html
docs/api/html/konval.sizeval-pysrc.html
docs/api/html/konval.sizeval.IsBetween-class.html
docs/api/html/konval.sizeval.IsEqualOrLess-class.html
docs/api/html/konval.sizeval.IsEqualOrMore-class.html
docs/api/html/konval.sizeval.IsInRange-class.html
docs/api/html/konval.sizeval.Length-class.html
docs/api/html/konval.stringval-module.html
docs/api/html/konval.stringval-pysrc.html
docs/api/html/konval.stringval.IsNonblank-class.html
docs/api/html/konval.stringval.IsPlainText-class.html
docs/api/html/konval.stringval.IsRegexMatch-class.html
docs/api/html/konval.stringval.Strip-class.html
konval.egg-info/PKG-INFO
konval.egg-info/SOURCES.txt
konval.egg-info/dependency_links.txt
konval.egg-info/entry_points.txt
konval.egg-info/not-zip-safe
konval.egg-info/top_level.txt