Metadata-Version: 1.0
Name: konval
Version: 0.3dev
Summary: Routines for data validation & conversion
Home-page: http://www.agapow.net/software/py-konval
Author: Paul-Michael Agapow
Author-email: pma@agapow.net
License: MIT
Keywords: validation conversion
Platform: UNKNOWN
Classifier: Development Status :: 3 - Alpha
Classifier: Natural Language :: English
Classifier: Topic :: Text Processing :: General
Classifier: Intended Audience :: Developers
Classifier: License :: OSI Approved :: MIT License
Classifier: Programming Language :: Python
Classifier: Operating System :: OS Independent
Classifier: Topic :: Text Processing :: Filters
